{"shell":true,"revision":"07c8d473512771ada016747d6d0eff6468a3c60c","objects":[{"type":null,"source":"lib/macros/dsl/moongate.ex:1","object_type":"ModuleObject","moduledoc":null,"module":"Elixir.Moongate","id":"Moongate"},{"type":null,"source":"lib/app.ex:1","object_type":"ModuleObject","moduledoc":null,"module":"Elixir.Moongate.Application","id":"Moongate.Application"},{"type":null,"source":"lib/auth/auth.ex:10","object_type":"ModuleObject","moduledoc":null,"module":"Elixir.Moongate.Auth","id":"Moongate.Auth"},{"type":null,"source":"lib/auth/auth.ex:1","object_type":"ModuleObject","moduledoc":null,"module":"Elixir.Moongate.AuthSessions","id":"Moongate.AuthSessions"},{"type":null,"source":"lib/auth/auth.ex:5","object_type":"ModuleObject","moduledoc":null,"module":"Elixir.Moongate.AuthToken","id":"Moongate.AuthToken"},{"type":null,"source":"lib/events/listener.ex:1","object_type":"ModuleObject","moduledoc":null,"module":"Elixir.Moongate.ClientEvent","id":"Moongate.ClientEvent"},{"type":null,"source":"lib/services/data.ex:1","object_type":"ModuleObject","moduledoc":null,"module":"Elixir.Moongate.Data","id":"Moongate.Data"},{"type":null,"source":"lib/db/models/user.ex:1","object_type":"ModuleObject","moduledoc":null,"module":"Elixir.Moongate.Db.User","id":"Moongate.Db.User"},{"type":null,"source":"lib/db/queries/users.ex:1","object_type":"ModuleObject","moduledoc":null,"module":"Elixir.Moongate.Db.UserQueries","id":"Moongate.Db.UserQueries"},{"type":null,"source":"lib/events/listener.ex:11","object_type":"ModuleObject","moduledoc":null,"module":"Elixir.Moongate.EventListener","id":"Moongate.EventListener"},{"type":null,"source":"lib/events/listener.ex:15","object_type":"ModuleObject","moduledoc":null,"module":"Elixir.Moongate.Events.Listener","id":"Moongate.Events.Listener"},{"type":null,"source":"lib/events/supervisor.ex:1","object_type":"ModuleObject","moduledoc":null,"module":"Elixir.Moongate.Events.Supervisor","id":"Moongate.Events.Supervisor"},{"type":null,"source":"lib/http/http.ex:1","object_type":"ModuleObject","moduledoc":null,"module":"Elixir.Moongate.HTTP","id":"Moongate.HTTP"},{"type":null,"source":"lib/http/header.ex:1","object_type":"ModuleObject","moduledoc":null,"module":"Elixir.Moongate.HTTP.Headers","id":"Moongate.HTTP.Headers"},{"type":null,"source":"lib/http/http.ex:5","object_type":"ModuleObject","moduledoc":null,"module":"Elixir.Moongate.HTTP.Host","id":"Moongate.HTTP.Host"},{"type":null,"source":"lib/macros/helper/external_resources.ex:1","object_type":"ModuleObject","moduledoc":null,"module":"Elixir.Moongate.Macros.ExternalResources","id":"Moongate.Macros.ExternalResources"},{"type":null,"source":"lib/macros/helper/processes.ex:9","object_type":"ModuleObject","moduledoc":null,"module":"Elixir.Moongate.Macros.Processes","id":"Moongate.Macros.Processes"},{"type":null,"source":"lib/macros/helper/socket_writer.ex:1","object_type":"ModuleObject","moduledoc":null,"module":"Elixir.Moongate.Macros.SocketWriter","id":"Moongate.Macros.SocketWriter"},{"type":null,"source":"lib/macros/helper/worlds.ex:1","object_type":"ModuleObject","moduledoc":null,"module":"Elixir.Moongate.Macros.Worlds","id":"Moongate.Macros.Worlds"},{"type":null,"source":"lib/services/packets.ex:1","object_type":"ModuleObject","moduledoc":null,"module":"Elixir.Moongate.Packets","id":"Moongate.Packets"},{"type":null,"source":"lib/macros/dsl/pool.ex:5","object_type":"ModuleObject","moduledoc":null,"module":"Elixir.Moongate.Pool","id":"Moongate.Pool"},{"type":null,"source":"lib/pools/pool.ex:1","object_type":"ModuleObject","moduledoc":null,"module":"Elixir.Moongate.PoolMutation","id":"Moongate.PoolMutation"},{"type":null,"source":"lib/pools/pool.ex:9","object_type":"ModuleObject","moduledoc":null,"module":"Elixir.Moongate.PoolState","id":"Moongate.PoolState"},{"type":null,"source":"lib/pools/pool.ex:24","object_type":"ModuleObject","moduledoc":null,"module":"Elixir.Moongate.Pools.Pool","id":"Moongate.Pools.Pool"},{"type":null,"source":"lib/pools/supervisor.ex:1","object_type":"ModuleObject","moduledoc":null,"module":"Elixir.Moongate.Pools.Supervisor","id":"Moongate.Pools.Supervisor"},{"type":null,"source":"lib/macros/helper/processes.ex:1","object_type":"ModuleObject","moduledoc":null,"module":"Elixir.Moongate.ProcessCapabilites","id":"Moongate.ProcessCapabilites"},{"type":null,"source":"lib/recursive/recursive.ex:5","object_type":"ModuleObject","moduledoc":null,"module":"Elixir.Moongate.Recursive","id":"Moongate.Recursive"},{"type":null,"source":"lib/recursive/supervisor.ex:1","object_type":"ModuleObject","moduledoc":null,"module":"Elixir.Moongate.Recursive.Supervisor","id":"Moongate.Recursive.Supervisor"},{"type":null,"source":"lib/recursive/recursive.ex:1","object_type":"ModuleObject","moduledoc":null,"module":"Elixir.Moongate.RecursiveSwitch","id":"Moongate.RecursiveSwitch"},{"type":null,"source":"lib/db/repo.ex:1","object_type":"ModuleObject","moduledoc":null,"module":"Elixir.Moongate.Repo","id":"Moongate.Repo"},{"type":null,"source":"lib/services/say.ex:1","object_type":"ModuleObject","moduledoc":null,"module":"Elixir.Moongate.Say","id":"Moongate.Say"},{"type":null,"source":"lib/scopes/events.ex:1","object_type":"ModuleObject","moduledoc":null,"module":"Elixir.Moongate.Scopes.Events","id":"Moongate.Scopes.Events"},{"type":null,"source":"lib/scopes/start.ex:1","object_type":"ModuleObject","moduledoc":null,"module":"Elixir.Moongate.Scopes.Start","id":"Moongate.Scopes.Start"},{"type":null,"source":"lib/sockets/sockets.ex:1","object_type":"ModuleObject","moduledoc":null,"module":"Elixir.Moongate.SocketOrigin","id":"Moongate.SocketOrigin"},{"type":null,"source":"lib/http/supervisor.ex:1","object_type":"ModuleObject","moduledoc":null,"module":"Elixir.Moongate.Sockets.HTTP.Supervisor","id":"Moongate.Sockets.HTTP.Supervisor"},{"type":null,"source":"lib/sockets/tcp/tcp.ex:5","object_type":"ModuleObject","moduledoc":null,"module":"Elixir.Moongate.Sockets.TCP.Socket","id":"Moongate.Sockets.TCP.Socket"},{"type":null,"source":"lib/sockets/tcp/supervisor.ex:1","object_type":"ModuleObject","moduledoc":null,"module":"Elixir.Moongate.Sockets.TCP.Supervisor","id":"Moongate.Sockets.TCP.Supervisor"},{"type":null,"source":"lib/sockets/udp/udp.ex:5","object_type":"ModuleObject","moduledoc":null,"module":"Elixir.Moongate.Sockets.UDP.Socket","id":"Moongate.Sockets.UDP.Socket"},{"type":null,"source":"lib/sockets/udp/supervisor.ex:1","object_type":"ModuleObject","moduledoc":null,"module":"Elixir.Moongate.Sockets.UDP.Supervisor","id":"Moongate.Sockets.UDP.Supervisor"},{"type":null,"source":"lib/sockets/web/web.ex:5","object_type":"ModuleObject","moduledoc":null,"module":"Elixir.Moongate.Sockets.Web.Socket","id":"Moongate.Sockets.Web.Socket"},{"type":null,"source":"lib/sockets/web/supervisor.ex:1","object_type":"ModuleObject","moduledoc":null,"module":"Elixir.Moongate.Sockets.Web.Supervisor","id":"Moongate.Sockets.Web.Supervisor"},{"type":null,"source":"lib/macros/dsl/stage.ex:1","object_type":"ModuleObject","moduledoc":null,"module":"Elixir.Moongate.Stage","id":"Moongate.Stage"},{"type":null,"source":"lib/stages/stage.ex:1","object_type":"ModuleObject","moduledoc":null,"module":"Elixir.Moongate.StageEvent","id":"Moongate.StageEvent"},{"type":null,"source":"lib/stages/stage.ex:5","object_type":"ModuleObject","moduledoc":null,"module":"Elixir.Moongate.StageInstance","id":"Moongate.StageInstance"},{"type":null,"source":"lib/stages/stage.ex:15","object_type":"ModuleObject","moduledoc":null,"module":"Elixir.Moongate.Stages.Instance","id":"Moongate.Stages.Instance"},{"type":null,"source":"lib/stages/supervisor.ex:1","object_type":"ModuleObject","moduledoc":null,"module":"Elixir.Moongate.Stages.Supervisor","id":"Moongate.Stages.Supervisor"},{"type":null,"source":"lib/supervisors/supervision_tree.ex:1","object_type":"ModuleObject","moduledoc":null,"module":"Elixir.Moongate.SupervisionTree","id":"Moongate.SupervisionTree"},{"type":null,"source":"lib/supervisors/supervisor.ex:1","object_type":"ModuleObject","moduledoc":null,"module":"Elixir.Moongate.Supervisor","id":"Moongate.Supervisor"},{"type":null,"source":"lib/macros/dsl/pool.ex:1","object_type":"ModuleObject","moduledoc":null,"module":"Elixir.Moongate.SyncEvent","id":"Moongate.SyncEvent"},{"type":null,"source":"lib/sockets/tcp/tcp.ex:1","object_type":"ModuleObject","moduledoc":null,"module":"Elixir.Moongate.TCPSocket","id":"Moongate.TCPSocket"},{"type":null,"source":"lib/services/time.ex:1","object_type":"ModuleObject","moduledoc":null,"module":"Elixir.Moongate.Time","id":"Moongate.Time"},{"type":null,"source":"lib/sockets/udp/udp.ex:1","object_type":"ModuleObject","moduledoc":null,"module":"Elixir.Moongate.UDPSocket","id":"Moongate.UDPSocket"},{"type":null,"source":"lib/sockets/web/web.ex:1","object_type":"ModuleObject","moduledoc":null,"module":"Elixir.Moongate.WebSocket","id":"Moongate.WebSocket"},{"type":"def","source":"lib/macros/dsl/moongate.ex:25","signature":[["event",[],null],["stage_name",[],null]],"object_type":"FunctionObject","name":"arrive","module_id":"Moongate","id":"arrive/2","doc":null,"arity":2},{"type":"def","source":"lib/macros/dsl/moongate.ex:21","signature":[["event",[],null]],"object_type":"FunctionObject","name":"depart","module_id":"Moongate","id":"depart/1","doc":null,"arity":1},{"type":"defmacro","source":"lib/macros/dsl/moongate.ex:4","signature":[["stage_map",[],null]],"object_type":"FunctionObject","name":"stages","module_id":"Moongate","id":"stages/1","doc":null,"arity":1},{"type":"defmacro","source":"lib/macros/dsl/moongate.ex:13","signature":[["stage_name",[],null]],"object_type":"FunctionObject","name":"you_start_on","module_id":"Moongate","id":"you_start_on/1","doc":null,"arity":1},{"type":"def","source":"lib/app.ex:10","signature":[["type",[],"Elixir"],["args",[],null]],"object_type":"FunctionObject","name":"start","module_id":"Moongate.Application","id":"start/2","doc":"  Initialize the game server.\n","arity":2},{"type":"def","source":"lib/app.ex:2","signature":[["state",[],"Elixir"]],"object_type":"FunctionObject","name":"stop","module_id":"Moongate.Application","id":"stop/1","doc":false,"arity":1},{"type":"def","source":"lib/app.ex:1","signature":[],"object_type":"FunctionObject","name":"world_name","module_id":"Moongate.Application","id":"world_name/0","doc":null,"arity":0},{"type":"def","source":"lib/auth/auth.ex:12","signature":[["old",[],"Elixir"],["state",[],null],["extra",[],"Elixir"]],"object_type":"FunctionObject","name":"code_change","module_id":"Moongate.Auth","id":"code_change/3","doc":false,"arity":3},{"type":"def","source":"lib/auth/auth.ex:12","signature":[["msg",[],null],["from",[],"Elixir"],["state",[],null]],"object_type":"FunctionObject","name":"handle_call","module_id":"Moongate.Auth","id":"handle_call/3","doc":"  Check whether a Moongate.SocketOrigin is authenticated.\n","arity":3},{"type":"def","source":"lib/auth/auth.ex:12","signature":[["msg",[],null],["state",[],null]],"object_type":"FunctionObject","name":"handle_cast","module_id":"Moongate.Auth","id":"handle_cast/2","doc":"  Create a new account with the given params if we're allowed.\n","arity":2},{"type":"def","source":"lib/auth/auth.ex:12","signature":[["msg",[],"Elixir"],["state",[],null]],"object_type":"FunctionObject","name":"handle_info","module_id":"Moongate.Auth","id":"handle_info/2","doc":false,"arity":2},{"type":"def","source":"lib/auth/auth.ex:12","signature":[["args",[],null]],"object_type":"FunctionObject","name":"init","module_id":"Moongate.Auth","id":"init/1","doc":false,"arity":1},{"type":"def","source":"lib/auth/auth.ex:15","signature":[["config",[],null]],"object_type":"FunctionObject","name":"start_link","module_id":"Moongate.Auth","id":"start_link/1","doc":null,"arity":1},{"type":"def","source":"lib/auth/auth.ex:12","signature":[["reason",[],"Elixir"],["state",[],"Elixir"]],"object_type":"FunctionObject","name":"terminate","module_id":"Moongate.Auth","id":"terminate/2","doc":false,"arity":2},{"type":"def","source":"lib/services/data.ex:7","signature":[["member",[],null]],"object_type":"FunctionObject","name":"condense_pool_member","module_id":"Moongate.Data","id":"condense_pool_member/1","doc":"  Remove any special attributes from a pool member's\n  keyword list, allowing it to be compared to items\n  within a pool's members list.\n","arity":1},{"type":"def","source":"lib/services/data.ex:11","signature":[["member",[],null],["key",[],null]],"object_type":"FunctionObject","name":"pool_member_attr","module_id":"Moongate.Data","id":"pool_member_attr/2","doc":null,"arity":2},{"type":"def","source":"lib/db/models/user.ex:1","signature":[["changeset",[],null]],"object_type":"FunctionObject","name":"before_insert","module_id":"Moongate.Db.User","id":"before_insert/1","doc":null,"arity":1},{"type":"def","source":"lib/db/models/user.ex:1","signature":[["changeset",[],null]],"object_type":"FunctionObject","name":"before_update","module_id":"Moongate.Db.User","id":"before_update/1","doc":null,"arity":1},{"type":"def","source":"lib/db/queries/users.ex:11","signature":[["params",[],null]],"object_type":"FunctionObject","name":"create","module_id":"Moongate.Db.UserQueries","id":"create/1","doc":null,"arity":1},{"type":"def","source":"lib/db/queries/users.ex:20","signature":[["id",[],null]],"object_type":"FunctionObject","name":"delete","module_id":"Moongate.Db.UserQueries","id":"delete/1","doc":null,"arity":1},{"type":"def","source":"lib/db/queries/users.ex:25","signature":[["email",[],null]],"object_type":"FunctionObject","name":"find_by_email","module_id":"Moongate.Db.UserQueries","id":"find_by_email/1","doc":null,"arity":1},{"type":"def","source":"lib/db/queries/users.ex:47","signature":[],"object_type":"FunctionObject","name":"generate_salt","module_id":"Moongate.Db.UserQueries","id":"generate_salt/0","doc":null,"arity":0},{"type":"def","source":"lib/db/queries/users.ex:33","signature":[["params",[],null]],"object_type":"FunctionObject","name":"generate_user","module_id":"Moongate.Db.UserQueries","id":"generate_user/1","doc":null,"arity":1},{"type":"def","source":"lib/events/listener.ex:17","signature":[["old",[],"Elixir"],["state",[],null],["extra",[],"Elixir"]],"object_type":"FunctionObject","name":"code_change","module_id":"Moongate.Events.Listener","id":"code_change/3","doc":false,"arity":3},{"type":"def","source":"lib/events/listener.ex:17","signature":[["msg",[],null],["from",[],"Elixir"],["state",[],null]],"object_type":"FunctionObject","name":"handle_call","module_id":"Moongate.Events.Listener","id":"handle_call/3","doc":"  Clean up\n","arity":3},{"type":"def","source":"lib/events/listener.ex:17","signature":[["msg",[],null],["state",[],null]],"object_type":"FunctionObject","name":"handle_cast","module_id":"Moongate.Events.Listener","id":"handle_cast/2","doc":"  Accept an incoming message.\n","arity":2},{"type":"def","source":"lib/events/listener.ex:17","signature":[["msg",[],"Elixir"],["state",[],null]],"object_type":"FunctionObject","name":"handle_info","module_id":"Moongate.Events.Listener","id":"handle_info/2","doc":false,"arity":2},{"type":"def","source":"lib/events/listener.ex:88","signature":[["origin",[],null],["cast",[],null],["params",[],null],["to",[],null],["logged_in",[],null]],"object_type":"FunctionObject","name":"handle_message","module_id":"Moongate.Events.Listener","id":"handle_message/5","doc":"  Handle an incoming, trusted message.\n","arity":5},{"type":"def","source":"lib/events/listener.ex:17","signature":[["args",[],null]],"object_type":"FunctionObject","name":"init","module_id":"Moongate.Events.Listener","id":"init/1","doc":false,"arity":1},{"type":"def","source":"lib/events/listener.ex:21","signature":[["origin",[],null]],"object_type":"FunctionObject","name":"start_link","module_id":"Moongate.Events.Listener","id":"start_link/1","doc":null,"arity":1},{"type":"def","source":"lib/events/listener.ex:17","signature":[["reason",[],"Elixir"],["state",[],"Elixir"]],"object_type":"FunctionObject","name":"terminate","module_id":"Moongate.Events.Listener","id":"terminate/2","doc":false,"arity":2},{"type":"def","source":"lib/events/supervisor.ex:11","signature":[["",[],"Elixir"]],"object_type":"FunctionObject","name":"init","module_id":"Moongate.Events.Supervisor","id":"init/1","doc":"  Prepare the events listener supervisor.\n","arity":1},{"type":"def","source":"lib/events/supervisor.ex:4","signature":[],"object_type":"FunctionObject","name":"start_link","module_id":"Moongate.Events.Supervisor","id":"start_link/0","doc":null,"arity":0},{"type":"def","source":"lib/http/header.ex:4","signature":[["req",[],null],["env",[],null]],"object_type":"FunctionObject","name":"execute","module_id":"Moongate.HTTP.Headers","id":"execute/2","doc":null,"arity":2},{"type":"def","source":"lib/http/http.ex:6","signature":[["old",[],"Elixir"],["state",[],null],["extra",[],"Elixir"]],"object_type":"FunctionObject","name":"code_change","module_id":"Moongate.HTTP.Host","id":"code_change/3","doc":false,"arity":3},{"type":"def","source":"lib/http/http.ex:6","signature":[["msg",[],null],["from",[],"Elixir"],["state",[],null]],"object_type":"FunctionObject","name":"handle_call","module_id":"Moongate.HTTP.Host","id":"handle_call/3","doc":false,"arity":3},{"type":"def","source":"lib/http/http.ex:6","signature":[["msg",[],null],["state",[],null]],"object_type":"FunctionObject","name":"handle_cast","module_id":"Moongate.HTTP.Host","id":"handle_cast/2","doc":false,"arity":2},{"type":"def","source":"lib/http/http.ex:6","signature":[["msg",[],"Elixir"],["state",[],null]],"object_type":"FunctionObject","name":"handle_info","module_id":"Moongate.HTTP.Host","id":"handle_info/2","doc":false,"arity":2},{"type":"def","source":"lib/http/http.ex:6","signature":[["args",[],null]],"object_type":"FunctionObject","name":"init","module_id":"Moongate.HTTP.Host","id":"init/1","doc":false,"arity":1},{"type":"def","source":"lib/http/http.ex:10","signature":[["arg1",[],"Elixir"]],"object_type":"FunctionObject","name":"start_link","module_id":"Moongate.HTTP.Host","id":"start_link/1","doc":null,"arity":1},{"type":"def","source":"lib/http/http.ex:6","signature":[["reason",[],"Elixir"],["state",[],"Elixir"]],"object_type":"FunctionObject","name":"terminate","module_id":"Moongate.HTTP.Host","id":"terminate/2","doc":false,"arity":2},{"type":"def","source":"lib/macros/helper/socket_writer.ex:2","signature":[["target",[],null],["tag",[],null],["message",[],null]],"object_type":"FunctionObject","name":"write_to","module_id":"Moongate.Macros.SocketWriter","id":"write_to/3","doc":null,"arity":3},{"type":"def","source":"lib/macros/helper/socket_writer.ex:5","signature":[["target",[],null],["tag",[],null],["name",[],null],["message",[],null]],"object_type":"FunctionObject","name":"write_to","module_id":"Moongate.Macros.SocketWriter","id":"write_to/4","doc":null,"arity":4},{"type":"def","source":"lib/macros/helper/socket_writer.ex:22","signature":[["target",[],null],["message",[],null]],"object_type":"FunctionObject","name":"write_to_tcp","module_id":"Moongate.Macros.SocketWriter","id":"write_to_tcp/2","doc":null,"arity":2},{"type":"def","source":"lib/macros/helper/socket_writer.ex:26","signature":[["target",[],null],["message",[],null]],"object_type":"FunctionObject","name":"write_to_udp","module_id":"Moongate.Macros.SocketWriter","id":"write_to_udp/2","doc":null,"arity":2},{"type":"def","source":"lib/macros/helper/socket_writer.ex:30","signature":[["target",[],null],["message",[],null]],"object_type":"FunctionObject","name":"write_to_web","module_id":"Moongate.Macros.SocketWriter","id":"write_to_web/2","doc":null,"arity":2},{"type":"def","source":"lib/services/packets.ex:5","signature":[["string",[],null]],"object_type":"FunctionObject","name":"parse","module_id":"Moongate.Packets","id":"parse/1","doc":"  Validate and parse an incoming packet.\n","arity":1},{"type":"def","source":"lib/services/packets.ex:34","signature":[["message",[],null]],"object_type":"FunctionObject","name":"sync","module_id":"Moongate.Packets","id":"sync/1","doc":"  This function takes a Moongate.SyncEvent which contains a list\n  of keys and a list of lists containing values mapped to those\n  keys. It generates a string representing these keys and the\n  members of the collection.\n","arity":1},{"type":"def","source":"lib/macros/dsl/pool.ex:50","signature":[["member",[],null],["key",[],null]],"object_type":"FunctionObject","name":"attr","module_id":"Moongate.Pool","id":"attr/2","doc":null,"arity":2},{"type":"defmacro","source":"lib/macros/dsl/pool.ex:8","signature":[["attribute_map",[],null]],"object_type":"FunctionObject","name":"attributes","module_id":"Moongate.Pool","id":"attributes/1","doc":null,"arity":1},{"type":"def","source":"lib/macros/dsl/pool.ex:85","signature":[["event",[],null],["key",[],null]],"object_type":"FunctionObject","name":"bubble","module_id":"Moongate.Pool","id":"bubble/2","doc":null,"arity":2},{"type":"def","source":"lib/macros/dsl/pool.ex:91","signature":[["event",[],null],["key",[],null],["params",[],null]],"object_type":"FunctionObject","name":"bubble","module_id":"Moongate.Pool","id":"bubble/3","doc":null,"arity":3},{"type":"defmacro","source":"lib/macros/dsl/pool.ex:32","signature":[["cascade_list",[],null]],"object_type":"FunctionObject","name":"cascades","module_id":"Moongate.Pool","id":"cascades/1","doc":null,"arity":1},{"type":"def","source":"lib/macros/dsl/pool.ex:97","signature":[["event",[],null],["params",[],null]],"object_type":"FunctionObject","name":"echo","module_id":"Moongate.Pool","id":"echo/2","doc":null,"arity":2},{"type":"def","source":"lib/macros/dsl/pool.ex:103","signature":[["delay",[],null],["event",[],null],["params",[],null]],"object_type":"FunctionObject","name":"echo_after","module_id":"Moongate.Pool","id":"echo_after/3","doc":null,"arity":3},{"type":"defmacro","source":"lib/macros/dsl/pool.ex:20","signature":[["target",[],null],["attribute",[],null],["delta",[],null],["params",[],null]],"object_type":"FunctionObject","name":"mutate","module_id":"Moongate.Pool","id":"mutate/4","doc":null,"arity":4},{"type":"defmacro","source":"lib/macros/dsl/pool.ex:26","signature":[["target",[],null],["attribute",[],null],["value",[],null]],"object_type":"FunctionObject","name":"set","module_id":"Moongate.Pool","id":"set/3","doc":null,"arity":3},{"type":"def","source":"lib/macros/dsl/pool.ex:60","signature":[["pool",[],null],["keys",[],null]],"object_type":"FunctionObject","name":"sync","module_id":"Moongate.Pool","id":"sync/2","doc":null,"arity":2},{"type":"def","source":"lib/macros/dsl/pool.ex:58","signature":[["event",[],null],["pool",[],null],["keys",[],null]],"object_type":"FunctionObject","name":"sync","module_id":"Moongate.Pool","id":"sync/3","doc":null,"arity":3},{"type":"def","source":"lib/macros/dsl/pool.ex:54","signature":[["event",[],null],["member",[],null],["message",[],null]],"object_type":"FunctionObject","name":"tagged","module_id":"Moongate.Pool","id":"tagged/3","doc":null,"arity":3},{"type":"def","source":"lib/macros/dsl/pool.ex:107","signature":[["member",[],null],["message",[],null]],"object_type":"FunctionObject","name":"tell","module_id":"Moongate.Pool","id":"tell/2","doc":null,"arity":2},{"type":"defmacro","source":"lib/macros/dsl/pool.ex:41","signature":[["touch_list",[],null]],"object_type":"FunctionObject","name":"touches","module_id":"Moongate.Pool","id":"touches/1","doc":null,"arity":1},{"type":"def","source":"lib/pools/pool.ex:26","signature":[["old",[],"Elixir"],["state",[],null],["extra",[],"Elixir"]],"object_type":"FunctionObject","name":"code_change","module_id":"Moongate.Pools.Pool","id":"code_change/3","doc":false,"arity":3},{"type":"def","source":"lib/pools/pool.ex:26","signature":[["msg",[],null],["from",[],"Elixir"],["state",[],null]],"object_type":"FunctionObject","name":"handle_call","module_id":"Moongate.Pools.Pool","id":"handle_call/3","doc":"  Synchronously call a function defined on the pool module,\n  replying with the result.\n","arity":3},{"type":"def","source":"lib/pools/pool.ex:26","signature":[["msg",[],null],["state",[],null]],"object_type":"FunctionObject","name":"handle_cast","module_id":"Moongate.Pools.Pool","id":"handle_cast/2","doc":"  Handle a pool member mutation event.\n","arity":2},{"type":"def","source":"lib/pools/pool.ex:26","signature":[["arg1",[],"Elixir"],["state",[],null]],"object_type":"FunctionObject","name":"handle_info","module_id":"Moongate.Pools.Pool","id":"handle_info/2","doc":"  Given a callback and a number of milliseconds, cascade that\n  callback as it is defined on the pool module on a timer\n  set to the interval provided.\n","arity":2},{"type":"def","source":"lib/pools/pool.ex:26","signature":[["args",[],null]],"object_type":"FunctionObject","name":"init","module_id":"Moongate.Pools.Pool","id":"init/1","doc":false,"arity":1},{"type":"def","source":"lib/pools/pool.ex:30","signature":[["arg1",[],"Elixir"]],"object_type":"FunctionObject","name":"start_link","module_id":"Moongate.Pools.Pool","id":"start_link/1","doc":null,"arity":1},{"type":"def","source":"lib/pools/pool.ex:26","signature":[["reason",[],"Elixir"],["state",[],"Elixir"]],"object_type":"FunctionObject","name":"terminate","module_id":"Moongate.Pools.Pool","id":"terminate/2","doc":false,"arity":2},{"type":"def","source":"lib/pools/pool.ex:312","signature":[["arg1",[],"Elixir"]],"object_type":"FunctionObject","name":"touch_test","module_id":"Moongate.Pools.Pool","id":"touch_test/1","doc":null,"arity":1},{"type":"def","source":"lib/pools/pool.ex:24","signature":[],"object_type":"FunctionObject","name":"world_name","module_id":"Moongate.Pools.Pool","id":"world_name/0","doc":null,"arity":0},{"type":"def","source":"lib/pools/supervisor.ex:11","signature":[["",[],"Elixir"]],"object_type":"FunctionObject","name":"init","module_id":"Moongate.Pools.Supervisor","id":"init/1","doc":"  Prepare the pools listener supervisor.\n","arity":1},{"type":"def","source":"lib/pools/supervisor.ex:4","signature":[],"object_type":"FunctionObject","name":"start_link","module_id":"Moongate.Pools.Supervisor","id":"start_link/0","doc":null,"arity":0},{"type":"def","source":"lib/recursive/recursive.ex:6","signature":[["old",[],"Elixir"],["state",[],null],["extra",[],"Elixir"]],"object_type":"FunctionObject","name":"code_change","module_id":"Moongate.Recursive","id":"code_change/3","doc":false,"arity":3},{"type":"def","source":"lib/recursive/recursive.ex:6","signature":[["msg",[],null],["from",[],"Elixir"],["state",[],null]],"object_type":"FunctionObject","name":"handle_call","module_id":"Moongate.Recursive","id":"handle_call/3","doc":false,"arity":3},{"type":"def","source":"lib/recursive/recursive.ex:6","signature":[["msg",[],null],["state",[],null]],"object_type":"FunctionObject","name":"handle_cast","module_id":"Moongate.Recursive","id":"handle_cast/2","doc":false,"arity":2},{"type":"def","source":"lib/recursive/recursive.ex:6","signature":[["msg",[],"Elixir"],["state",[],null]],"object_type":"FunctionObject","name":"handle_info","module_id":"Moongate.Recursive","id":"handle_info/2","doc":false,"arity":2},{"type":"def","source":"lib/recursive/recursive.ex:6","signature":[["args",[],null]],"object_type":"FunctionObject","name":"init","module_id":"Moongate.Recursive","id":"init/1","doc":false,"arity":1},{"type":"def","source":"lib/recursive/recursive.ex:9","signature":[["arg1",[],"Elixir"]],"object_type":"FunctionObject","name":"start_link","module_id":"Moongate.Recursive","id":"start_link/1","doc":null,"arity":1},{"type":"def","source":"lib/recursive/recursive.ex:6","signature":[["reason",[],"Elixir"],["state",[],"Elixir"]],"object_type":"FunctionObject","name":"terminate","module_id":"Moongate.Recursive","id":"terminate/2","doc":false,"arity":2},{"type":"def","source":"lib/recursive/supervisor.ex:11","signature":[["",[],"Elixir"]],"object_type":"FunctionObject","name":"init","module_id":"Moongate.Recursive.Supervisor","id":"init/1","doc":"  Prepare the HTTP server supervisor.\n","arity":1},{"type":"def","source":"lib/recursive/supervisor.ex:4","signature":[],"object_type":"FunctionObject","name":"start_link","module_id":"Moongate.Recursive.Supervisor","id":"start_link/0","doc":null,"arity":0},{"type":"def","source":"lib/db/repo.ex:2","signature":[["queryable",[],null],["\\\\",[],[["opts",[],null],[]]]],"object_type":"FunctionObject","name":"all","module_id":"Moongate.Repo","id":"all/2","doc":false,"arity":2},{"type":"def","source":"lib/db/repo.ex:2","signature":[],"object_type":"FunctionObject","name":"config","module_id":"Moongate.Repo","id":"config/0","doc":false,"arity":0},{"type":"def","source":"lib/db/repo.ex:2","signature":[["model",[],null],["\\\\",[],[["opts",[],null],[]]]],"object_type":"FunctionObject","name":"delete","module_id":"Moongate.Repo","id":"delete/2","doc":false,"arity":2},{"type":"def","source":"lib/db/repo.ex:2","signature":[["model",[],null],["\\\\",[],[["opts",[],null],[]]]],"object_type":"FunctionObject","name":"delete!","module_id":"Moongate.Repo","id":"delete!/2","doc":false,"arity":2},{"type":"def","source":"lib/db/repo.ex:2","signature":[["queryable",[],null],["\\\\",[],[["opts",[],null],[]]]],"object_type":"FunctionObject","name":"delete_all","module_id":"Moongate.Repo","id":"delete_all/2","doc":false,"arity":2},{"type":"def","source":"lib/db/repo.ex:2","signature":[["queryable",[],null],["id",[],null],["\\\\",[],[["opts",[],null],[]]]],"object_type":"FunctionObject","name":"get","module_id":"Moongate.Repo","id":"get/3","doc":false,"arity":3},{"type":"def","source":"lib/db/repo.ex:2","signature":[["queryable",[],null],["id",[],null],["\\\\",[],[["opts",[],null],[]]]],"object_type":"FunctionObject","name":"get!","module_id":"Moongate.Repo","id":"get!/3","doc":false,"arity":3},{"type":"def","source":"lib/db/repo.ex:2","signature":[["queryable",[],null],["clauses",[],null],["\\\\",[],[["opts",[],null],[]]]],"object_type":"FunctionObject","name":"get_by","module_id":"Moongate.Repo","id":"get_by/3","doc":false,"arity":3},{"type":"def","source":"lib/db/repo.ex:2","signature":[["queryable",[],null],["clauses",[],null],["\\\\",[],[["opts",[],null],[]]]],"object_type":"FunctionObject","name":"get_by!","module_id":"Moongate.Repo","id":"get_by!/3","doc":false,"arity":3},{"type":"def","source":"lib/db/repo.ex:2","signature":[["model",[],null],["\\\\",[],[["opts",[],null],[]]]],"object_type":"FunctionObject","name":"insert","module_id":"Moongate.Repo","id":"insert/2","doc":false,"arity":2},{"type":"def","source":"lib/db/repo.ex:2","signature":[["model",[],null],["\\\\",[],[["opts",[],null],[]]]],"object_type":"FunctionObject","name":"insert!","module_id":"Moongate.Repo","id":"insert!/2","doc":false,"arity":2},{"type":"def","source":"lib/db/repo.ex:2","signature":[["entry",[],null]],"object_type":"FunctionObject","name":"log","module_id":"Moongate.Repo","id":"log/1","doc":false,"arity":1},{"type":"def","source":"lib/db/repo.ex:2","signature":[["queryable",[],null],["\\\\",[],[["opts",[],null],[]]]],"object_type":"FunctionObject","name":"one","module_id":"Moongate.Repo","id":"one/2","doc":false,"arity":2},{"type":"def","source":"lib/db/repo.ex:2","signature":[["queryable",[],null],["\\\\",[],[["opts",[],null],[]]]],"object_type":"FunctionObject","name":"one!","module_id":"Moongate.Repo","id":"one!/2","doc":false,"arity":2},{"type":"def","source":"lib/db/repo.ex:2","signature":[["model_or_models",[],null],["preloads",[],null]],"object_type":"FunctionObject","name":"preload","module_id":"Moongate.Repo","id":"preload/2","doc":false,"arity":2},{"type":"def","source":"lib/db/repo.ex:2","signature":[["value",[],null]],"object_type":"FunctionObject","name":"rollback","module_id":"Moongate.Repo","id":"rollback/1","doc":false,"arity":1},{"type":"def","source":"lib/db/repo.ex:2","signature":[["\\\\",[],[["opts",[],null],[]]]],"object_type":"FunctionObject","name":"start_link","module_id":"Moongate.Repo","id":"start_link/1","doc":null,"arity":1},{"type":"def","source":"lib/db/repo.ex:2","signature":[["pid",[],null],["\\\\",[],[["timeout",[],null],5000]]],"object_type":"FunctionObject","name":"stop","module_id":"Moongate.Repo","id":"stop/2","doc":false,"arity":2},{"type":"def","source":"lib/db/repo.ex:2","signature":[["\\\\",[],[["opts",[],null],[]]],["fun",[],null]],"object_type":"FunctionObject","name":"transaction","module_id":"Moongate.Repo","id":"transaction/2","doc":false,"arity":2},{"type":"def","source":"lib/db/repo.ex:2","signature":[["model",[],null],["\\\\",[],[["opts",[],null],[]]]],"object_type":"FunctionObject","name":"update","module_id":"Moongate.Repo","id":"update/2","doc":false,"arity":2},{"type":"def","source":"lib/db/repo.ex:2","signature":[["model",[],null],["\\\\",[],[["opts",[],null],[]]]],"object_type":"FunctionObject","name":"update!","module_id":"Moongate.Repo","id":"update!/2","doc":false,"arity":2},{"type":"def","source":"lib/db/repo.ex:2","signature":[["queryable",[],null],["updates",[],null],["\\\\",[],[["opts",[],null],[]]]],"object_type":"FunctionObject","name":"update_all","module_id":"Moongate.Repo","id":"update_all/3","doc":false,"arity":3},{"type":"def","source":"lib/services/say.ex:5","signature":[],"object_type":"FunctionObject","name":"greeting","module_id":"Moongate.Say","id":"greeting/0","doc":"  A greeting message, output when the server is started.\n","arity":0},{"type":"def","source":"lib/services/say.ex:44","signature":[["o",[],null]],"object_type":"FunctionObject","name":"origin","module_id":"Moongate.Say","id":"origin/1","doc":"  Given a Moongate.SocketOrigin, return the appropriate\n  string to use to represent that origin.\n","arity":1},{"type":"def","source":"lib/services/say.ex:14","signature":[["string",[],null],["modifier",[],null]],"object_type":"FunctionObject","name":"pretty","module_id":"Moongate.Say","id":"pretty/2","doc":null,"arity":2},{"type":"def","source":"lib/services/say.ex:21","signature":[["string",[],null],["modifier",[],null],["options",[],null]],"object_type":"FunctionObject","name":"pretty","module_id":"Moongate.Say","id":"pretty/3","doc":"  Format and output a colorized ANSI string.\n","arity":3},{"type":"def","source":"lib/scopes/events.ex:8","signature":[["message",[],"Elixir"]],"object_type":"FunctionObject","name":"take","module_id":"Moongate.Scopes.Events","id":"take/1","doc":"  This is called when a socket message is received by a\n  client and the server has no defined way of dealing with\n  it. This is overriden by the Moongate.Scopes.Events within\n  the world's server/scopes directory.\n","arity":1},{"type":"def","source":"lib/scopes/start.ex:7","signature":[],"object_type":"FunctionObject","name":"on_load","module_id":"Moongate.Scopes.Start","id":"on_load/0","doc":"  This is called when the game server first loads. This is\n  overriden by the Moongate.Scopes.Start within the world's\n  server/scopes directory.\n","arity":0},{"type":"def","source":"lib/http/supervisor.ex:11","signature":[["",[],"Elixir"]],"object_type":"FunctionObject","name":"init","module_id":"Moongate.Sockets.HTTP.Supervisor","id":"init/1","doc":"  Prepare the HTTP server supervisor.\n","arity":1},{"type":"def","source":"lib/http/supervisor.ex:4","signature":[],"object_type":"FunctionObject","name":"start_link","module_id":"Moongate.Sockets.HTTP.Supervisor","id":"start_link/0","doc":null,"arity":0},{"type":"def","source":"lib/sockets/tcp/tcp.ex:6","signature":[["old",[],"Elixir"],["state",[],null],["extra",[],"Elixir"]],"object_type":"FunctionObject","name":"code_change","module_id":"Moongate.Sockets.TCP.Socket","id":"code_change/3","doc":false,"arity":3},{"type":"def","source":"lib/sockets/tcp/tcp.ex:6","signature":[["msg",[],null],["from",[],"Elixir"],["state",[],null]],"object_type":"FunctionObject","name":"handle_call","module_id":"Moongate.Sockets.TCP.Socket","id":"handle_call/3","doc":false,"arity":3},{"type":"def","source":"lib/sockets/tcp/tcp.ex:6","signature":[["msg",[],null],["state",[],null]],"object_type":"FunctionObject","name":"handle_cast","module_id":"Moongate.Sockets.TCP.Socket","id":"handle_cast/2","doc":false,"arity":2},{"type":"def","source":"lib/sockets/tcp/tcp.ex:6","signature":[["msg",[],"Elixir"],["state",[],null]],"object_type":"FunctionObject","name":"handle_info","module_id":"Moongate.Sockets.TCP.Socket","id":"handle_info/2","doc":false,"arity":2},{"type":"def","source":"lib/sockets/tcp/tcp.ex:6","signature":[["args",[],null]],"object_type":"FunctionObject","name":"init","module_id":"Moongate.Sockets.TCP.Socket","id":"init/1","doc":false,"arity":1},{"type":"def","source":"lib/sockets/tcp/tcp.ex:12","signature":[["port",[],null]],"object_type":"FunctionObject","name":"start_link","module_id":"Moongate.Sockets.TCP.Socket","id":"start_link/1","doc":"  Listen for incoming socket messages on a port.\n","arity":1},{"type":"def","source":"lib/sockets/tcp/tcp.ex:6","signature":[["reason",[],"Elixir"],["state",[],"Elixir"]],"object_type":"FunctionObject","name":"terminate","module_id":"Moongate.Sockets.TCP.Socket","id":"terminate/2","doc":false,"arity":2},{"type":"def","source":"lib/sockets/tcp/supervisor.ex:11","signature":[["",[],"Elixir"]],"object_type":"FunctionObject","name":"init","module_id":"Moongate.Sockets.TCP.Supervisor","id":"init/1","doc":"  Prepare the sockets listener supervisor.\n","arity":1},{"type":"def","source":"lib/sockets/tcp/supervisor.ex:4","signature":[],"object_type":"FunctionObject","name":"start_link","module_id":"Moongate.Sockets.TCP.Supervisor","id":"start_link/0","doc":null,"arity":0},{"type":"def","source":"lib/sockets/udp/udp.ex:6","signature":[["old",[],"Elixir"],["state",[],null],["extra",[],"Elixir"]],"object_type":"FunctionObject","name":"code_change","module_id":"Moongate.Sockets.UDP.Socket","id":"code_change/3","doc":false,"arity":3},{"type":"def","source":"lib/sockets/udp/udp.ex:6","signature":[["msg",[],null],["from",[],"Elixir"],["state",[],null]],"object_type":"FunctionObject","name":"handle_call","module_id":"Moongate.Sockets.UDP.Socket","id":"handle_call/3","doc":false,"arity":3},{"type":"def","source":"lib/sockets/udp/udp.ex:6","signature":[["msg",[],null],["state",[],null]],"object_type":"FunctionObject","name":"handle_cast","module_id":"Moongate.Sockets.UDP.Socket","id":"handle_cast/2","doc":false,"arity":2},{"type":"def","source":"lib/sockets/udp/udp.ex:6","signature":[["msg",[],"Elixir"],["state",[],null]],"object_type":"FunctionObject","name":"handle_info","module_id":"Moongate.Sockets.UDP.Socket","id":"handle_info/2","doc":false,"arity":2},{"type":"def","source":"lib/sockets/udp/udp.ex:20","signature":[["arg1",[],"Elixir"],["server",[],null]],"object_type":"FunctionObject","name":"handler","module_id":"Moongate.Sockets.UDP.Socket","id":"handler/2","doc":null,"arity":2},{"type":"def","source":"lib/sockets/udp/udp.ex:6","signature":[["args",[],null]],"object_type":"FunctionObject","name":"init","module_id":"Moongate.Sockets.UDP.Socket","id":"init/1","doc":false,"arity":1},{"type":"def","source":"lib/sockets/udp/udp.ex:9","signature":[["port",[],null]],"object_type":"FunctionObject","name":"start_link","module_id":"Moongate.Sockets.UDP.Socket","id":"start_link/1","doc":null,"arity":1},{"type":"def","source":"lib/sockets/udp/udp.ex:6","signature":[["reason",[],"Elixir"],["state",[],"Elixir"]],"object_type":"FunctionObject","name":"terminate","module_id":"Moongate.Sockets.UDP.Socket","id":"terminate/2","doc":false,"arity":2},{"type":"def","source":"lib/sockets/udp/udp.ex:42","signature":[["server",[],null]],"object_type":"FunctionObject","name":"udp_listen","module_id":"Moongate.Sockets.UDP.Socket","id":"udp_listen/1","doc":null,"arity":1},{"type":"def","source":"lib/sockets/udp/supervisor.ex:11","signature":[["",[],"Elixir"]],"object_type":"FunctionObject","name":"init","module_id":"Moongate.Sockets.UDP.Supervisor","id":"init/1","doc":"  Prepare the sockets listener supervisor.\n","arity":1},{"type":"def","source":"lib/sockets/udp/supervisor.ex:4","signature":[],"object_type":"FunctionObject","name":"start_link","module_id":"Moongate.Sockets.UDP.Supervisor","id":"start_link/0","doc":null,"arity":0},{"type":"def","source":"lib/sockets/web/web.ex:6","signature":[["old",[],"Elixir"],["state",[],null],["extra",[],"Elixir"]],"object_type":"FunctionObject","name":"code_change","module_id":"Moongate.Sockets.Web.Socket","id":"code_change/3","doc":false,"arity":3},{"type":"def","source":"lib/sockets/web/web.ex:6","signature":[["msg",[],null],["from",[],"Elixir"],["state",[],null]],"object_type":"FunctionObject","name":"handle_call","module_id":"Moongate.Sockets.Web.Socket","id":"handle_call/3","doc":false,"arity":3},{"type":"def","source":"lib/sockets/web/web.ex:6","signature":[["msg",[],null],["state",[],null]],"object_type":"FunctionObject","name":"handle_cast","module_id":"Moongate.Sockets.Web.Socket","id":"handle_cast/2","doc":false,"arity":2},{"type":"def","source":"lib/sockets/web/web.ex:6","signature":[["msg",[],"Elixir"],["state",[],null]],"object_type":"FunctionObject","name":"handle_info","module_id":"Moongate.Sockets.Web.Socket","id":"handle_info/2","doc":false,"arity":2},{"type":"def","source":"lib/sockets/web/web.ex:6","signature":[["args",[],null]],"object_type":"FunctionObject","name":"init","module_id":"Moongate.Sockets.Web.Socket","id":"init/1","doc":false,"arity":1},{"type":"def","source":"lib/sockets/web/web.ex:9","signature":[["port",[],null]],"object_type":"FunctionObject","name":"start_link","module_id":"Moongate.Sockets.Web.Socket","id":"start_link/1","doc":null,"arity":1},{"type":"def","source":"lib/sockets/web/web.ex:6","signature":[["reason",[],"Elixir"],["state",[],"Elixir"]],"object_type":"FunctionObject","name":"terminate","module_id":"Moongate.Sockets.Web.Socket","id":"terminate/2","doc":false,"arity":2},{"type":"def","source":"lib/sockets/web/supervisor.ex:11","signature":[["",[],"Elixir"]],"object_type":"FunctionObject","name":"init","module_id":"Moongate.Sockets.Web.Supervisor","id":"init/1","doc":"  Prepare the sockets listener supervisor.\n","arity":1},{"type":"def","source":"lib/sockets/web/supervisor.ex:4","signature":[],"object_type":"FunctionObject","name":"start_link","module_id":"Moongate.Sockets.Web.Supervisor","id":"start_link/0","doc":null,"arity":0},{"type":"def","source":"lib/macros/dsl/stage.ex:4","signature":[["event",[],null],["stage_name",[],null]],"object_type":"FunctionObject","name":"arrive","module_id":"Moongate.Stage","id":"arrive/2","doc":null,"arity":2},{"type":"defmacro","source":"lib/macros/dsl/stage.ex:35","signature":[["event",[],null],["target",[],null],["callback",[],null],["params",[],null]],"object_type":"FunctionObject","name":"call","module_id":"Moongate.Stage","id":"call/4","doc":null,"arity":4},{"type":"defmacro","source":"lib/macros/dsl/stage.ex:42","signature":[["event",[],null],["target",[],null],["callback",[],null]],"object_type":"FunctionObject","name":"cast","module_id":"Moongate.Stage","id":"cast/3","doc":null,"arity":3},{"type":"defmacro","source":"lib/macros/dsl/stage.ex:49","signature":[["event",[],null],["target",[],null],["callback",[],null],["params",[],null]],"object_type":"FunctionObject","name":"cast","module_id":"Moongate.Stage","id":"cast/4","doc":null,"arity":4},{"type":"def","source":"lib/macros/dsl/stage.ex:9","signature":[["event",[],null]],"object_type":"FunctionObject","name":"depart","module_id":"Moongate.Stage","id":"depart/1","doc":null,"arity":1},{"type":"defmacro","source":"lib/macros/dsl/stage.ex:56","signature":[["event",[],null],["target",[],null]],"object_type":"FunctionObject","name":"drop","module_id":"Moongate.Stage","id":"drop/2","doc":null,"arity":2},{"type":"defmacro","source":"lib/macros/dsl/stage.ex:63","signature":[["module_name",[],null],["params",[],null]],"object_type":"FunctionObject","name":"find","module_id":"Moongate.Stage","id":"find/2","doc":null,"arity":2},{"type":"defmacro","source":"lib/macros/dsl/stage.ex:71","signature":[["module_name",[],null],["params",[],null]],"object_type":"FunctionObject","name":"first","module_id":"Moongate.Stage","id":"first/2","doc":null,"arity":2},{"type":"def","source":"lib/macros/dsl/stage.ex:14","signature":[["t",[],null]],"object_type":"FunctionObject","name":"is_authenticated?","module_id":"Moongate.Stage","id":"is_authenticated?/1","doc":null,"arity":1},{"type":"defmacro","source":"lib/macros/dsl/stage.ex:78","signature":[["stage_meta",[],null]],"object_type":"FunctionObject","name":"meta","module_id":"Moongate.Stage","id":"meta/1","doc":null,"arity":1},{"type":"defmacro","source":"lib/macros/dsl/stage.ex:87","signature":[["event",[],null],["module_name",[],null],["params",[],null]],"object_type":"FunctionObject","name":"new","module_id":"Moongate.Stage","id":"new/3","doc":null,"arity":3},{"type":"def","source":"lib/macros/dsl/stage.ex:19","signature":[["module_name",[],null]],"object_type":"FunctionObject","name":"pool_name","module_id":"Moongate.Stage","id":"pool_name/1","doc":null,"arity":1},{"type":"defmacro","source":"lib/macros/dsl/stage.ex:94","signature":[["pool_list",[],null]],"object_type":"FunctionObject","name":"pools","module_id":"Moongate.Stage","id":"pools/1","doc":null,"arity":1},{"type":"def","source":"lib/macros/dsl/stage.ex:27","signature":[["max",[],null]],"object_type":"FunctionObject","name":"random","module_id":"Moongate.Stage","id":"random/1","doc":null,"arity":1},{"type":"def","source":"lib/macros/dsl/stage.ex:31","signature":[["items",[],null]],"object_type":"FunctionObject","name":"random_from","module_id":"Moongate.Stage","id":"random_from/1","doc":null,"arity":1},{"type":"defmacro","source":"lib/macros/dsl/stage.ex:103","signature":[["message",[],null],["callback",[],null]],"object_type":"FunctionObject","name":"takes","module_id":"Moongate.Stage","id":"takes/2","doc":null,"arity":2},{"type":"defmacro","source":"lib/macros/dsl/stage.ex:109","signature":[["message",[],null],["callback",[],null],["params",[],null]],"object_type":"FunctionObject","name":"takes","module_id":"Moongate.Stage","id":"takes/3","doc":null,"arity":3},{"type":"def","source":"lib/stages/stage.ex:17","signature":[["old",[],"Elixir"],["state",[],null],["extra",[],"Elixir"]],"object_type":"FunctionObject","name":"code_change","module_id":"Moongate.Stages.Instance","id":"code_change/3","doc":false,"arity":3},{"type":"def","source":"lib/stages/stage.ex:17","signature":[["msg",[],null],["from",[],"Elixir"],["state",[],null]],"object_type":"FunctionObject","name":"handle_call","module_id":"Moongate.Stages.Instance","id":"handle_call/3","doc":false,"arity":3},{"type":"def","source":"lib/stages/stage.ex:17","signature":[["msg",[],null],["state",[],null]],"object_type":"FunctionObject","name":"handle_cast","module_id":"Moongate.Stages.Instance","id":"handle_cast/2","doc":"  Receive a message from an event listener and if the origin on the\n  event is qualified, call the callback defined on the stage\n  module.\n","arity":2},{"type":"def","source":"lib/stages/stage.ex:17","signature":[["msg",[],"Elixir"],["state",[],null]],"object_type":"FunctionObject","name":"handle_info","module_id":"Moongate.Stages.Instance","id":"handle_info/2","doc":false,"arity":2},{"type":"def","source":"lib/stages/stage.ex:17","signature":[["args",[],null]],"object_type":"FunctionObject","name":"init","module_id":"Moongate.Stages.Instance","id":"init/1","doc":false,"arity":1},{"type":"def","source":"lib/stages/stage.ex:117","signature":[["pool_module",[],null],["state",[],null]],"object_type":"FunctionObject","name":"initialize_pool","module_id":"Moongate.Stages.Instance","id":"initialize_pool/2","doc":"  Initialize one pool.\n","arity":2},{"type":"def","source":"lib/stages/stage.ex:108","signature":[["state",[],null]],"object_type":"FunctionObject","name":"initialize_pools","module_id":"Moongate.Stages.Instance","id":"initialize_pools/1","doc":"  Initialize all pools.\n","arity":1},{"type":"def","source":"lib/stages/stage.ex:20","signature":[["params",[],null]],"object_type":"FunctionObject","name":"start_link","module_id":"Moongate.Stages.Instance","id":"start_link/1","doc":null,"arity":1},{"type":"def","source":"lib/stages/stage.ex:17","signature":[["reason",[],"Elixir"],["state",[],"Elixir"]],"object_type":"FunctionObject","name":"terminate","module_id":"Moongate.Stages.Instance","id":"terminate/2","doc":false,"arity":2},{"type":"def","source":"lib/stages/supervisor.ex:11","signature":[["",[],"Elixir"]],"object_type":"FunctionObject","name":"init","module_id":"Moongate.Stages.Supervisor","id":"init/1","doc":"  Prepare the events listener supervisor.\n","arity":1},{"type":"def","source":"lib/stages/supervisor.ex:4","signature":[],"object_type":"FunctionObject","name":"start_link","module_id":"Moongate.Stages.Supervisor","id":"start_link/0","doc":null,"arity":0},{"type":"def","source":"lib/supervisors/supervision_tree.ex:2","signature":[["old",[],"Elixir"],["state",[],null],["extra",[],"Elixir"]],"object_type":"FunctionObject","name":"code_change","module_id":"Moongate.SupervisionTree","id":"code_change/3","doc":false,"arity":3},{"type":"def","source":"lib/supervisors/supervision_tree.ex:2","signature":[["msg",[],null],["from",[],"Elixir"],["state",[],null]],"object_type":"FunctionObject","name":"handle_call","module_id":"Moongate.SupervisionTree","id":"handle_call/3","doc":"  Spawn a new child within the requested supervisor.\n","arity":3},{"type":"def","source":"lib/supervisors/supervision_tree.ex:2","signature":[["msg",[],null],["state",[],null]],"object_type":"FunctionObject","name":"handle_cast","module_id":"Moongate.SupervisionTree","id":"handle_cast/2","doc":"  Cast on all children of a supervisor.\n","arity":2},{"type":"def","source":"lib/supervisors/supervision_tree.ex:2","signature":[["msg",[],"Elixir"],["state",[],null]],"object_type":"FunctionObject","name":"handle_info","module_id":"Moongate.SupervisionTree","id":"handle_info/2","doc":false,"arity":2},{"type":"def","source":"lib/supervisors/supervision_tree.ex:2","signature":[["args",[],null]],"object_type":"FunctionObject","name":"init","module_id":"Moongate.SupervisionTree","id":"init/1","doc":false,"arity":1},{"type":"def","source":"lib/supervisors/supervision_tree.ex:5","signature":[],"object_type":"FunctionObject","name":"start_link","module_id":"Moongate.SupervisionTree","id":"start_link/0","doc":null,"arity":0},{"type":"def","source":"lib/supervisors/supervision_tree.ex:2","signature":[["reason",[],"Elixir"],["state",[],"Elixir"]],"object_type":"FunctionObject","name":"terminate","module_id":"Moongate.SupervisionTree","id":"terminate/2","doc":false,"arity":2},{"type":"def","source":"lib/supervisors/supervisor.ex:15","signature":[["arg1",[],"Elixir"]],"object_type":"FunctionObject","name":"init","module_id":"Moongate.Supervisor","id":"init/1","doc":"  Prepare the supervision tree.\n","arity":1},{"type":"def","source":"lib/supervisors/supervisor.ex:4","signature":[["arg1",[],"Elixir"]],"object_type":"FunctionObject","name":"start_link","module_id":"Moongate.Supervisor","id":"start_link/1","doc":null,"arity":1},{"type":"def","source":"lib/supervisors/supervisor.ex:36","signature":[["arg1",[],"Elixir"]],"object_type":"FunctionObject","name":"supervisor_from","module_id":"Moongate.Supervisor","id":"supervisor_from/1","doc":null,"arity":1},{"type":"def","source":"lib/supervisors/supervisor.ex:32","signature":[["world_supervisors",[],null]],"object_type":"FunctionObject","name":"supervisors_from","module_id":"Moongate.Supervisor","id":"supervisors_from/1","doc":null,"arity":1},{"type":"def","source":"lib/services/time.ex:4","signature":[],"object_type":"FunctionObject","name":"current_ms","module_id":"Moongate.Time","id":"current_ms/0","doc":null,"arity":0},{"type":"def","source":"lib/services/time.ex:8","signature":[],"object_type":"FunctionObject","name":"now_formatted","module_id":"Moongate.Time","id":"now_formatted/0","doc":null,"arity":0}],"language":"elixir","git_repo_url":"https://github.com/supernintendo/moongate.git","client_version":"0.4.0","client_name":"inch_ex","branch_name":"master","args":[]}